edu_calc/__init__.py
edu_calc/__main__.py
edu_calc/core.py
edu_calc_setuptools-0.1.0.dist-info/METADATA
edu_calc_setuptools-0.1.0.dist-info/WHEEL
edu_calc_setuptools-0.1.0.dist-info/entry_points.txt
edu_calc_setuptools-0.1.0.dist-info/top_level.txt
edu_calc_setuptools-0.1.0.dist-info/RECORD
